.gitignore
LICENSE
MANIFEST.in
README.md
setup.py
bernhard/__init__.py
bernhard/pb.py
bernhard/proto_pb2.py
bernhard.egg-info/PKG-INFO
bernhard.egg-info/SOURCES.txt
bernhard.egg-info/dependency_links.txt
bernhard.egg-info/not-zip-safe
bernhard.egg-info/requires.txt
bernhard.egg-info/top_level.txt