Metadata-Version: 1.1
Name: bernhard
Version: 0.2.6
Summary: Python client for Riemann
Home-page: http://github.com/banjiewen/bernhard.git
Author: Benjamin Anderspn
Author-email: b@banjiewen.net
License: ASF2.0
Platform: UNKNOWN
Classifier: Development Status :: 4 - Beta
Classifier: Environment :: Other Environment
Classifier: Intended Audience :: Developers
Classifier: License :: OSI Approved :: Apache Software License
Classifier: Operating System :: MacOS :: MacOS X
Classifier: Operating System :: POSIX
Classifier: Operating System :: Unix
Classifier: Programming Language :: Python
Classifier: Programming Language :: Python :: 2
Classifier: Programming Language :: Python :: 3
Classifier: Topic :: Internet :: Log Analysis
Classifier: Topic :: Utilities
Classifier: Topic :: System :: Networking :: Monitoring
